{
  "updated_at": "2026-04-21T04:50:14.100532+00:00",
  "games": [
    {
      "id": "d1a7a6e7b024f888e922a62b14fcf466",
      "home_team": "Boston Celtics",
      "away_team": "Philadelphia 76ers",
      "commence_time": "2026-04-21T23:10:00Z",
      "time_et": "7:10 PM ET",
      "live": {
        "state": "pre",
        "period": 0,
        "clock": "",
        "home_score": null,
        "away_score": null
      },
      "home_stats": {
        "conference": "—",
        "record": "—",
        "seed": "—",
        "ppg": "—",
        "papg": "—",
        "diff": "—",
        "home_rec": "—",
        "away_rec": "—",
        "streak": "—",
        "forma": []
      },
      "away_stats": {
        "conference": "—",
        "record": "—",
        "seed": "—",
        "ppg": "—",
        "papg": "—",
        "diff": "—",
        "home_rec": "—",
        "away_rec": "—",
        "streak": "—",
        "forma": []
      },
      "home_injuries": [],
      "away_injuries": [],
      "injuries": [],
      "alerta": false,
      "alerta_msg": "",
      "odds": {
        "home_ml": -850,
        "away_ml": 660,
        "spread_home": -13.5,
        "total_ou": 216.5,
        "best_book": "DraftKings",
        "num_books": 9
      },
      "recomendacion": {
        "pick": "Sin pick",
        "tipo": "NO BET",
        "confianza": "—",
        "ev": null,
        "prob_modelo": 50.0,
        "prob_mercado": 87.2,
        "notas": "Diferencia modelo/mercado excesiva (37%) — mercado probablemente incorporó bajas u otra info reciente. | Modelo local: 50.0% | Mercado: 87.2%",
        "spread_lado": null,
        "spread_ev": null,
        "spread_conf": "—",
        "spread_notas": "Sin datos para spread.",
        "ou_pick": null,
        "ou_ev": null,
        "ou_confianza": "—",
        "ou_notas": "Sin datos.",
        "home_pra_out": 0,
        "away_pra_out": 0
      }
    },
    {
      "id": "680084e4612c197a1cf4170d82ba6f10",
      "home_team": "San Antonio Spurs",
      "away_team": "Portland Trail Blazers",
      "commence_time": "2026-04-22T00:00:00Z",
      "time_et": "8:00 PM ET",
      "live": {
        "state": "pre",
        "period": 0,
        "clock": "",
        "home_score": null,
        "away_score": null
      },
      "home_stats": {
        "conference": "—",
        "record": "—",
        "seed": "—",
        "ppg": "—",
        "papg": "—",
        "diff": "—",
        "home_rec": "—",
        "away_rec": "—",
        "streak": "—",
        "forma": []
      },
      "away_stats": {
        "conference": "—",
        "record": "—",
        "seed": "—",
        "ppg": "—",
        "papg": "—",
        "diff": "—",
        "home_rec": "—",
        "away_rec": "—",
        "streak": "—",
        "forma": []
      },
      "home_injuries": [],
      "away_injuries": [],
      "injuries": [],
      "alerta": false,
      "alerta_msg": "",
      "odds": {
        "home_ml": -640,
        "away_ml": 500,
        "spread_home": -11.5,
        "total_ou": 220.5,
        "best_book": "LowVig.ag",
        "num_books": 9
      },
      "recomendacion": {
        "pick": "Sin pick",
        "tipo": "NO BET",
        "confianza": "—",
        "ev": null,
        "prob_modelo": 50.0,
        "prob_mercado": 83.8,
        "notas": "Diferencia modelo/mercado excesiva (34%) — mercado probablemente incorporó bajas u otra info reciente. | Modelo local: 50.0% | Mercado: 83.8%",
        "spread_lado": null,
        "spread_ev": null,
        "spread_conf": "—",
        "spread_notas": "Sin datos para spread.",
        "ou_pick": null,
        "ou_ev": null,
        "ou_confianza": "—",
        "ou_notas": "Sin datos.",
        "home_pra_out": 0,
        "away_pra_out": 0
      }
    },
    {
      "id": "d3d28b764e5099920880de59a45e82cf",
      "home_team": "Los Angeles Lakers",
      "away_team": "Houston Rockets",
      "commence_time": "2026-04-22T02:40:00Z",
      "time_et": "10:40 PM ET",
      "live": {
        "state": "pre",
        "period": 0,
        "clock": "",
        "home_score": null,
        "away_score": null
      },
      "home_stats": {
        "conference": "—",
        "record": "—",
        "seed": "—",
        "ppg": "—",
        "papg": "—",
        "diff": "—",
        "home_rec": "—",
        "away_rec": "—",
        "streak": "—",
        "forma": []
      },
      "away_stats": {
        "conference": "—",
        "record": "—",
        "seed": "—",
        "ppg": "—",
        "papg": "—",
        "diff": "—",
        "home_rec": "—",
        "away_rec": "—",
        "streak": "—",
        "forma": []
      },
      "home_injuries": [],
      "away_injuries": [],
      "injuries": [],
      "alerta": false,
      "alerta_msg": "",
      "odds": {
        "home_ml": 182,
        "away_ml": -192,
        "spread_home": 4.5,
        "total_ou": 206.5,
        "best_book": "LowVig.ag",
        "num_books": 9
      },
      "recomendacion": {
        "pick": "Los Angeles Lakers",
        "tipo": "ML Lakers",
        "confianza": "alta",
        "ev": 41.0,
        "prob_modelo": 50.0,
        "prob_mercado": 35.0,
        "notas": "Modelo: 50.0% | Mercado: 35.0% | Edge: +15.0%",
        "spread_lado": null,
        "spread_ev": null,
        "spread_conf": "—",
        "spread_notas": "Sin datos para spread.",
        "ou_pick": null,
        "ou_ev": null,
        "ou_confianza": "—",
        "ou_notas": "Sin datos.",
        "home_pra_out": 0,
        "away_pra_out": 0
      }
    }
  ]
}